Changelog.txt
LICENSE
MANIFEST.in
README.md
setup.py
bin/booktool
pdfbooktool/__init__.py
pdfbooktool/functions.py
pdfbooktool.egg-info/PKG-INFO
pdfbooktool.egg-info/SOURCES.txt
pdfbooktool.egg-info/dependency_links.txt
pdfbooktool.egg-info/requires.txt
pdfbooktool.egg-info/top_level.txt