Metadata-Version: 1.1
Name: pdfbooktool
Version: 0.1.3
Summary: Tool for formatting A6 PDFs into A4 ready for printing A6 books.
Home-page: https://github.com/morngrar/pdfbooktool
Author: Svein-Kåre Bjørnsen
Author-email: sveinkare@gmail.com
License: GPL
Platform: UNKNOWN
Classifier: Development Status :: 4 - Beta
Classifier: License :: OSI Approved :: GNU General Public License v3 (GPLv3)
Classifier: Programming Language :: Python :: 3 :: Only
Classifier: Topic :: Printing
Classifier: Topic :: Utilities
